cidan/__init__.py
cidan/__main__.py
cidan/GUI/MainWindow.py
cidan/GUI/__init__.py
cidan/GUI/Console/ConsoleWidget.py
cidan/GUI/Console/__init__.py
cidan/GUI/Data_Interaction/CalculateSingleTrialThread.py
cidan/GUI/Data_Interaction/DataHandler.py
cidan/GUI/Data_Interaction/DemoDownloadThread.py
cidan/GUI/Data_Interaction/OpenDatasetThread.py
cidan/GUI/Data_Interaction/PreprocessThread.py
cidan/GUI/Data_Interaction/ROIExtractionThread.py
cidan/GUI/Data_Interaction/ROIExtractionWorker.py
cidan/GUI/Data_Interaction/Signals.py
cidan/GUI/Data_Interaction/Thread.py
cidan/GUI/Data_Interaction/TimeTraceCalculateThread.py
cidan/GUI/Data_Interaction/Worker.py
cidan/GUI/Data_Interaction/__init__.py
cidan/GUI/Data_Interaction/demoDownload.py
cidan/GUI/Data_Interaction/loadDataset.py
cidan/GUI/Data_Interaction/neurofinder_edited.py
cidan/GUI/Data_Interaction/data_handler_functions/__init__.py
cidan/GUI/Data_Interaction/data_handler_functions/change_param.py
cidan/GUI/Data_Interaction/data_handler_functions/export.py
cidan/GUI/Data_Interaction/data_handler_functions/gen_rois_functions.py
cidan/GUI/Data_Interaction/data_handler_functions/load_filter_functions.py
cidan/GUI/Data_Interaction/data_handler_functions/save_functions.py
cidan/GUI/Data_Interaction/data_handler_functions/time_trace_functions.py
cidan/GUI/EventFilter/EventFilterMainWindow.py
cidan/GUI/EventFilter/__init__.py
cidan/GUI/ImageView/ImageViewModule.py
cidan/GUI/ImageView/ROIImageViewModule.py
cidan/GUI/ImageView/ROIPaintImageViewModule.py
cidan/GUI/ImageView/__init__.py
cidan/GUI/Inputs/BoolInput.py
cidan/GUI/Inputs/ColorInput.py
cidan/GUI/Inputs/FileInput.py
cidan/GUI/Inputs/FloatInput.py
cidan/GUI/Inputs/Input.py
cidan/GUI/Inputs/Int3DInput.py
cidan/GUI/Inputs/IntInput.py
cidan/GUI/Inputs/IntRangeInput.py
cidan/GUI/Inputs/OptionInput.py
cidan/GUI/Inputs/StringInput.py
cidan/GUI/Inputs/__init__.py
cidan/GUI/ListWidgets/ClassItemModule.py
cidan/GUI/ListWidgets/ClassItemWidget.py
cidan-0.1.37.dist-info/LICENSE
cidan-0.1.37.dist-info/METADATA
cidan-0.1.37.dist-info/WHEEL
cidan-0.1.37.dist-info/entry_points.txt
cidan-0.1.37.dist-info/top_level.txt
cidan-0.1.37.dist-info/RECORD
